gradescent/__init__.py
gradescent/optimizer.py
gradescent-0.9.4.dist-info/LICENSE
gradescent-0.9.4.dist-info/METADATA
gradescent-0.9.4.dist-info/WHEEL
gradescent-0.9.4.dist-info/top_level.txt
gradescent-0.9.4.dist-info/RECORD
