Metadata-Version: 2.1
Name: gradescent
Version: 0.9.4
Summary: optimization of multivariate functions by gradient descent
Home-page: https://github.com/andromed2/gradescent
Author: Andreas Neumann
Author-email: andromed@web.de
License: UNKNOWN
Platform: UNKNOWN
Classifier: Programming Language :: Python :: 3
Classifier: License :: OSI Approved :: GNU General Public License v3 (GPLv3)
Classifier: Operating System :: OS Independent
Requires-Python: >=3.6
